cookie_cloud/__init__.py
cookie_cloud/generate.py
cookie_cloud/util.py
cookie_cloud-0.1.13.dist-info/LICENSE
cookie_cloud-0.1.13.dist-info/METADATA
cookie_cloud-0.1.13.dist-info/WHEEL
cookie_cloud-0.1.13.dist-info/entry_points.txt
cookie_cloud-0.1.13.dist-info/top_level.txt
cookie_cloud-0.1.13.dist-info/RECORD
